lens/__init__.py
lens/etch.py
lens/lens.py
simplelens-1.2.1.dist-info/METADATA
simplelens-1.2.1.dist-info/WHEEL
simplelens-1.2.1.dist-info/top_level.txt
simplelens-1.2.1.dist-info/RECORD
