Metadata-Version: 2.4
Name: simplelens
Version: 1.2.1
Summary: Implementation of the lens functional pattern
Requires-Python: >=3.11
Requires-Dist: build==1.2.1
